bidamic/__init__.py
bidamic/bidamic.py
bidamic_challenge-1.0.1.dist-info/LICENSE
bidamic_challenge-1.0.1.dist-info/METADATA
bidamic_challenge-1.0.1.dist-info/WHEEL
bidamic_challenge-1.0.1.dist-info/top_level.txt
bidamic_challenge-1.0.1.dist-info/RECORD
