Metadata-Version: 2.1
Name: bidamic-challenge
Version: 1.0.1
Summary: A python package for calculating ROAS
Home-page: https://github.com/MichaelQuant4R/bidamic_test_1
Author: Michael S. Russell
Author-email: michael.r2014@yahoo.co.uk
License: MIT
Platform: UNKNOWN
Classifier: License :: OSI Approved :: MIT License
Classifier: Programming Language :: Python :: 3.0
Classifier: Programming Language :: Python :: 3.7
Classifier: Programming Language :: Python :: 3.8
Classifier: Programming Language :: Python :: 3.9
License-File: LICENSE
Requires-Dist: numpy
Requires-Dist: pandas
